 [
    {
        "title": "Data Engineering",
        "subtitle": "Let us get the best out of your data with:",
        "items":[
            {"tit":"Exploratory data analysis"},
            {"tit":"Data cleaning"},
            {"tit":"Anonymization"},
            {"tit":"ETL design"},            
            {"tit":"Data infrastructure design and build"},
            {"tit":"Data visualization"}
        ]
    },
    {
        "title": "Smart Services",
        "subtitle": "Build smart apps from the start with:",
        "items":[
            {"tit":"Architecture and Model Design"},
            {"tit":"Model build, training, and optimization"},
            {"tit":"Design and deploy data pipelines"},
            {"tit":"Built-in observability and monitoring"}
        ]
    },
    {
        "title": "Machine Learning Full Scope",
        "subtitle": "We can also offer you an end-to-end solution with:",
        "items":[
            {"tit":"Data Management in your business"},
            {"tit":"Data Integrations and APIs"},
            {"tit":"Web solutions centered on data management"},
            {"tit":"ML infrastructure design for cloud/on-premises arch"},
            {"tit":"Web interfaces for man-in-the-loop AI systems"},
            {"tit":"Machine learning-related consulting services"}
        ]
    }
]
